mseep_zettelkasten_mcp-1.2.1.dist-info/licenses/LICENSE
src/__init__.py
src/zettelkasten_mcp/__init__.py
src/zettelkasten_mcp/config.py
src/zettelkasten_mcp/dev.py
src/zettelkasten_mcp/main.py
src/zettelkasten_mcp/utils.py
src/zettelkasten_mcp/models/__init__.py
src/zettelkasten_mcp/models/db_models.py
src/zettelkasten_mcp/models/schema.py
src/zettelkasten_mcp/server/__init__.py
src/zettelkasten_mcp/server/mcp_server.py
src/zettelkasten_mcp/services/__init__.py
src/zettelkasten_mcp/services/search_service.py
src/zettelkasten_mcp/services/zettel_service.py
src/zettelkasten_mcp/storage/__init__.py
src/zettelkasten_mcp/storage/base.py
src/zettelkasten_mcp/storage/note_repository.py
mseep_zettelkasten_mcp-1.2.1.dist-info/METADATA
mseep_zettelkasten_mcp-1.2.1.dist-info/WHEEL
mseep_zettelkasten_mcp-1.2.1.dist-info/top_level.txt
mseep_zettelkasten_mcp-1.2.1.dist-info/RECORD
