Metadata-Version: 2.4
Name: mseep-zettelkasten-mcp
Version: 1.2.1
Summary: A Zettelkasten knowledge management system as an MCP server
Home-page: https://github.com/mseep
Author: mseep
Author-email: support@skydeck.ai
Maintainer: mseep
Maintainer-email: support@skydeck.ai
Keywords: mseep
Classifier: Programming Language :: Python :: 3
Classifier: License :: OSI Approved :: MIT License
Classifier: Operating System :: OS Independent
Requires-Python: >=3.6
License-File: LICENSE
Requires-Dist: mcp[cli]>=1.2.0
Requires-Dist: sqlalchemy>=2.0.0
Requires-Dist: pydantic>=2.0.0
Requires-Dist: python-frontmatter>=1.0.0
Requires-Dist: markdown>=3.4.0
Requires-Dist: python-dotenv>=1.0.0
Dynamic: author
Dynamic: author-email
Dynamic: classifier
Dynamic: description
Dynamic: description-content-type
Dynamic: home-page
Dynamic: keywords
Dynamic: license-file
Dynamic: maintainer
Dynamic: maintainer-email
Dynamic: requires-dist
Dynamic: requires-python
Dynamic: summary
